buyrandom3/__init__.py
buyrandom3/cli.py
buyrandom3/core.py
buyrandom3-0.5.22.dist-info/LICENSE
buyrandom3-0.5.22.dist-info/METADATA
buyrandom3-0.5.22.dist-info/WHEEL
buyrandom3-0.5.22.dist-info/top_level.txt
buyrandom3-0.5.22.dist-info/RECORD
