Metadata-Version: 2.1
Name: buyrandom3
Version: 0.5.22
Summary: some buy, some random.
Author-email: Tomás NAVARRETE GUTIÉRREZ <tngTUDOR@users.noreply.github.com>
Maintainer-email: Tomás NAVARRETE GUTIÉRREZ <tngTUDOR@users.noreply.github.com>
Project-URL: source, https://github.com/tngTUDOR/buyrandom3
Project-URL: homepage, https://github.com/tngTUDOR/buyrandom3
Project-URL: tracker, https://github.com/tngTUDOR/buyrandom3/issues
Classifier: Development Status :: 4 - Beta
Classifier: Programming Language :: Python
Classifier: Programming Language :: Python :: 3
Classifier: Programming Language :: Python :: 3.9
Classifier: Programming Language :: Python :: 3.10
Classifier: Programming Language :: Python :: 3.11
Classifier: Programming Language :: Python :: 3.12
Classifier: Natural Language :: English
Classifier: Operating System :: OS Independent
Classifier: Topic :: Scientific/Engineering
Requires-Python: >=3.9
License-File: LICENSE
Requires-Dist: click
Provides-Extra: dev
Requires-Dist: build ; extra == 'dev'
Requires-Dist: pre-commit ; extra == 'dev'
Requires-Dist: pylint ; extra == 'dev'
Requires-Dist: pytest ; extra == 'dev'
Requires-Dist: pytest-cov ; extra == 'dev'
Requires-Dist: pytest-randomly ; extra == 'dev'
Requires-Dist: setuptools ; extra == 'dev'
Provides-Extra: testing
Requires-Dist: buyrandom3 ; extra == 'testing'
Requires-Dist: pytest ; extra == 'testing'
Requires-Dist: pytest-cov ; extra == 'testing'
Requires-Dist: python-coveralls ; extra == 'testing'
